bedrock/__init__.py
bedrock/ags3.py
bedrock_systems-0.0.1a0.dist-info/LICENSE
bedrock_systems-0.0.1a0.dist-info/METADATA
bedrock_systems-0.0.1a0.dist-info/WHEEL
bedrock_systems-0.0.1a0.dist-info/top_level.txt
bedrock_systems-0.0.1a0.dist-info/RECORD
