Metadata-Version: 2.1
Name: bedrock-systems
Version: 0.0.1a0
Summary: Bedrock helps you work with geotechnical data
Author: Bedrock Systems
License: Apache Software License (Apache 2.0)
Project-URL: Homepage, https://bedrock.streamlit.app/
Project-URL: Source, https://github.com/bedrock-systems/bedrockpy
Project-URL: Documentation, https://github.com/bedrock-systems/bedrockpy
Project-URL: Tracker, https://github.com/bedrock-systems/bedrockpy/issues
Keywords: bedrock,geotechnical data,ags,geotechnical engineering,engineering geology,ground engineering
Classifier: Development Status :: 2 - Pre-Alpha
Classifier: License :: OSI Approved :: Apache Software License
Classifier: Programming Language :: Python
Classifier: Programming Language :: Python :: 3
Requires-Python: >=3.9
License-File: LICENSE
Requires-Dist: pandas
Provides-Extra: dev
Requires-Dist: ruff ; extra == 'dev'
Requires-Dist: mypy ; extra == 'dev'
Requires-Dist: bumpver ; extra == 'dev'
Requires-Dist: pip-tools ; extra == 'dev'
Requires-Dist: pytest ; extra == 'dev'
